semidv/Device.py
semidv/Material.py
semidv/Solve.py
semidv/Visual.py
semidv/__init__.py
semidv-1.0.7.dist-info/licenses/LICENSE
semidv-1.0.7.dist-info/METADATA
semidv-1.0.7.dist-info/WHEEL
semidv-1.0.7.dist-info/top_level.txt
semidv-1.0.7.dist-info/RECORD
