Metadata-Version: 2.4
Name: semidv
Version: 1.0.7
Summary: This is SEMIDV: a semiconductor device simulator
Author-email: Chien-Ting Tung <cttung@berkeley.edu>
License: MIT License
Requires-Python: >=3.6
License-File: LICENSE
Requires-Dist: scipy
Requires-Dist: cython
Requires-Dist: fdint
Dynamic: license-file
